trailhead_scraper.py
trailhead_scraper-0.1.1.dist-info/LICENSE
trailhead_scraper-0.1.1.dist-info/WHEEL
trailhead_scraper-0.1.1.dist-info/METADATA
trailhead_scraper-0.1.1.dist-info/RECORD
