Metadata-Version: 2.1
Name: trailhead-scraper
Version: 0.1.1
Summary: Retrieve public data from Salesforce Trailhead user profiles
Home-page: https://github.com/ang3orge/trailhead-scraper
License: MIT
Keywords: salesforce,trailhead,scraper
Author: Aaron George
Author-email: angeorge.dev@gmail.com
Requires-Python: >=3.6,<4.0
Classifier: License :: OSI Approved :: MIT License
Classifier: Programming Language :: Python :: 3
Classifier: Programming Language :: Python :: 3.6
Classifier: Programming Language :: Python :: 3.7
Classifier: Programming Language :: Python :: 3.8
Classifier: Programming Language :: Python :: 3.9
Requires-Dist: requests (>=2.25.0,<3.0.0)
Project-URL: Repository, https://github.com/ang3orge/trailhead-scraper
